spectrum_api_service/__init__.py
spectrum_api_service/constants/__init__.py
spectrum_api_service/constants/spectrum_constants.py
spectrum_api_service/helpers/__init__.py
spectrum_api_service/helpers/json_helper.py
spectrum_api_service/helpers/xml_helper.py
spectrum_api_service/models/__init__.py
spectrum_api_service/models/host_model.py
spectrum_api_service/models/host_spectrum_model.py
spectrum_api_service/models/spectrum_alarm_model.py
spectrum_api_service/models/spectrum_event_model.py
spectrum_api_service/services/__init__.py
spectrum_api_service/services/spectrum_api_service.py
spectrum_api_service_bit3-1.0.2.3.dist-info/METADATA
spectrum_api_service_bit3-1.0.2.3.dist-info/WHEEL
spectrum_api_service_bit3-1.0.2.3.dist-info/top_level.txt
spectrum_api_service_bit3-1.0.2.3.dist-info/RECORD
