Metadata-Version: 2.1
Name: spectrum-api-service-bit3
Version: 1.0.2.3
Summary: Es un paquete que tiene como propósito facilitar la comunicación con la API de SPECTRUM a través de Python. 
Home-page: https://github.com/bitcubico/SpectrumApiServicePy
Author: Mauricio Montoya Medrano
Author-email: mcubico33@gmail.com
License: UNKNOWN
Keywords: python,spectrum,api,arus,mcubico
Platform: UNKNOWN
Classifier: Development Status :: 4 - Beta
Classifier: Programming Language :: Python :: 3.8
Classifier: License :: OSI Approved :: MIT License
Classifier: Operating System :: MacOS :: MacOS X
Classifier: Operating System :: Microsoft :: Windows
Classifier: Operating System :: Unix
Requires-Python: >=3.8
Requires-Dist: lxml (>=4.6.2)
Requires-Dist: requests (>=2.25.1)
Requires-Dist: setuptools (>=53.0.0)
Requires-Dist: log-helper-bit3 (>=1.2.0)
